trytond/modules/akademy_classe/LICENSE
trytond/modules/akademy_classe/README.md
trytond/modules/akademy_classe/__init__.py
trytond/modules/akademy_classe/classe.py
trytond/modules/akademy_classe/classe.xml
trytond/modules/akademy_classe/company.py
trytond/modules/akademy_classe/company.xml
trytond/modules/akademy_classe/configuration.py
trytond/modules/akademy_classe/configuration.xml
trytond/modules/akademy_classe/configuration_data.xml
trytond/modules/akademy_classe/report.py
trytond/modules/akademy_classe/report.xml
trytond/modules/akademy_classe/tryton.cfg
trytond/modules/akademy_classe/variables.py
trytond/modules/akademy_classe/locale/en.po
trytond/modules/akademy_classe/locale/fr.po
trytond/modules/akademy_classe/locale/pt.po
trytond/modules/akademy_classe/reports/academic_level.fodt
trytond/modules/akademy_classe/reports/classes.fodt
trytond/modules/akademy_classe/reports/classes_student_timerule.fodt
trytond/modules/akademy_classe/reports/classes_students.fodt
trytond/modules/akademy_classe/reports/classes_teacher_timerule.fodt
trytond/modules/akademy_classe/reports/classes_teachers.fodt
trytond/modules/akademy_classe/reports/classes_timerule.fodt
trytond/modules/akademy_classe/reports/discipline_lessons.fodt
trytond/modules/akademy_classe/reports/matriculation.fodt
trytond/modules/akademy_classe/reports/matriculation_state.fodt
trytond/modules/akademy_classe/reports/matriculation_teacher.fodt
trytond/modules/akademy_classe/reports/studyplan.fodt
trytond/modules/akademy_classe/security/access_rights_admin.xml
trytond/modules/akademy_classe/security/access_rights_direct.xml
trytond/modules/akademy_classe/security/access_rights_secret.xml
trytond/modules/akademy_classe/security/access_rights_student.xml
trytond/modules/akademy_classe/security/access_rights_teacher.xml
trytond/modules/akademy_classe/tests/__init__.py
trytond/modules/akademy_classe/tests/test_classe.py
trytond/modules/akademy_classe/tests/test_company.py
akademy_classe-1.1.0.dist-info/METADATA
akademy_classe-1.1.0.dist-info/WHEEL
akademy_classe-1.1.0.dist-info/licenses/LICENSE
akademy_classe-1.1.0.dist-info/RECORD
